mathy_project/__init__.py
mathy_project-0.1.2.dist-info/LICENSE.txt
mathy_project-0.1.2.dist-info/METADATA
mathy_project-0.1.2.dist-info/WHEEL
mathy_project-0.1.2.dist-info/top_level.txt
mathy_project-0.1.2.dist-info/RECORD
